{"version":2,"structures":[{"name":"A0CommandCentre","id":118,"position":[12928,13440],"rotation":0,"startpos":0},{"name":"A0ComDroidControl","id":119,"position":[12416,13440],"rotation":0,"startpos":0},{"name":"A0ResourceExtractor","id":125,"position":[12352,12608],"rotation":0,"startpos":0},{"name":"A0ResourceExtractor","id":126,"position":[12480,12608],"rotation":0,"startpos":0},{"name":"A0ResourceExtractor","id":127,"position":[12608,12608],"rotation":0,"startpos":0},{"name":"A0ResourceExtractor","id":128,"position":[12736,12608],"rotation":0,"startpos":0},{"name":"A0ResourceExtractor","id":129,"position":[12864,12608],"rotation":0,"startpos":0},{"name":"A0ResourceExtractor","id":130,"position":[12992,12608],"rotation":0,"startpos":0},{"name":"A0ResourceExtractor","id":131,"position":[13120,12608],"rotation":0,"startpos":0},{"name":"A0ResourceExtractor","id":132,"position":[13248,12608],"rotation":0,"startpos":0},{"name":"A0ResourceExtractor","id":133,"position":[13376,12608],"rotation":0,"startpos":0},{"name":"A0ResourceExtractor","id":134,"position":[13504,12608],"rotation":0,"startpos":0},{"name":"A0ResourceExtractor","id":135,"position":[12352,12864],"rotation":0,"startpos":0},{"name":"A0ResourceExtractor","id":136,"position":[12480,12864],"rotation":0,"startpos":0},{"name":"A0ResourceExtractor","id":137,"position":[12608,12864],"rotation":0,"startpos":0},{"name":"A0ResourceExtractor","id":138,"position":[12736,12864],"rotation":0,"startpos":0},{"name":"A0ResourceExtractor","id":139,"position":[12864,12864],"rotation":0,"startpos":0},{"name":"A0ResourceExtractor","id":140,"position":[12992,12864],"rotation":0,"startpos":0},{"name":"A0ResourceExtractor","id":141,"position":[13120,12864],"rotation":0,"startpos":0},{"name":"A0ResourceExtractor","id":142,"position":[13248,12864],"rotation":0,"startpos":0},{"name":"A0ResourceExtractor","id":143,"position":[13376,12864],"rotation":0,"startpos":0},{"name":"A0ResourceExtractor","id":144,"position":[13504,12864],"rotation":0,"startpos":0},{"name":"A0PowerGenerator","id":145,"position":[12160,12288],"rotation":0,"startpos":0},{"name":"A0PowerGenerator","id":146,"position":[12544,12288],"rotation":0,"startpos":0},{"name":"A0PowerGenerator","id":147,"position":[12928,12288],"rotation":0,"startpos":0},{"name":"A0PowerGenerator","id":148,"position":[13312,12288],"rotation":0,"startpos":0},{"name":"A0PowerGenerator","id":149,"position":[13696,12288],"rotation":0,"startpos":0},{"name":"A0ResearchFacility","id":155,"position":[12160,11904],"rotation":0,"startpos":0},{"name":"A0ResearchFacility","id":156,"position":[12544,11904],"rotation":0,"startpos":0},{"name":"A0ResearchFacility","id":157,"position":[12928,11904],"rotation":0,"startpos":0},{"name":"A0ResearchFacility","id":158,"position":[13312,11904],"rotation":0,"startpos":0},{"name":"A0ResearchFacility","id":159,"position":[13696,11904],"rotation":0,"startpos":0},{"name":"A0CommandCentre","id":167,"position":[1920,1664],"rotation":0,"startpos":1},{"name":"A0CommandCentre","id":176,"position":[11648,1664],"rotation":0,"startpos":2},{"name":"A0CommandCentre","id":177,"position":[23680,2048],"rotation":0,"startpos":3},{"name":"A0CommandCentre","id":186,"position":[24064,13056],"rotation":0,"startpos":4},{"name":"A0CommandCentre","id":187,"position":[23424,23808],"rotation":0,"startpos":5},{"name":"A0CommandCentre","id":196,"position":[12800,23680],"rotation":0,"startpos":6},{"name":"A0CommandCentre","id":197,"position":[2176,23808],"rotation":0,"startpos":7},{"name":"A0CommandCentre","id":206,"position":[1792,12032],"rotation":0,"startpos":8},{"name":"A0BaBaFactory","id":207,"position":[6400,6336],"rotation":0,"player":"scavenger"},{"name":"A0BaBaFactory","id":208,"position":[19200,6336],"rotation":0,"player":"scavenger"},{"name":"A0BaBaFactory","id":209,"position":[19072,19264],"rotation":0,"player":"scavenger"},{"name":"A0BaBaFactory","id":210,"position":[6272,19264],"rotation":0,"player":"scavenger"},{"name":"A0BaBaPowerGenerator","id":211,"position":[6464,19136],"rotation":0,"player":"scavenger"},{"name":"A0BaBaPowerGenerator","id":212,"position":[6336,6592],"rotation":0,"player":"scavenger"},{"name":"A0BaBaPowerGenerator","id":213,"position":[19136,6592],"rotation":0,"player":"scavenger"},{"name":"A0BaBaPowerGenerator","id":214,"position":[19392,19392],"rotation":0,"player":"scavenger"},{"name":"A0PowMod1","id":219,"position":[12160,12288],"rotation":0,"startpos":0},{"name":"A0PowMod1","id":220,"position":[12544,12288],"rotation":0,"startpos":0},{"name":"A0PowMod1","id":221,"position":[12928,12288],"rotation":0,"startpos":0},{"name":"A0PowMod1","id":222,"position":[13312,12288],"rotation":0,"startpos":0},{"name":"A0PowMod1","id":223,"position":[13696,12288],"rotation":0,"startpos":0},{"name":"A0ResearchModule1","id":224,"position":[12160,11904],"rotation":0,"startpos":0},{"name":"A0ResearchModule1","id":225,"position":[12544,11904],"rotation":0,"startpos":0},{"name":"A0ResearchModule1","id":226,"position":[12928,11904],"rotation":0,"startpos":0},{"name":"A0ResearchModule1","id":227,"position":[13312,11904],"rotation":0,"startpos":0},{"name":"A0ResearchModule1","id":228,"position":[13696,11904],"rotation":0,"startpos":0}]}